RadGlio/__init__.py
radglio_data_preparation-0.1.dist-info/LICENSE
radglio_data_preparation-0.1.dist-info/METADATA
radglio_data_preparation-0.1.dist-info/WHEEL
radglio_data_preparation-0.1.dist-info/top_level.txt
radglio_data_preparation-0.1.dist-info/RECORD
