Metadata-Version: 2.1
Name: radglio-data-preparation
Version: 0.1
Summary: Brain Tumor MR data Preparation
Author: Sougata Maity
Author-email: maitysougata724@gmail.com
Classifier: Programming Language :: Python :: 3
Classifier: License :: OSI Approved :: MIT License
Classifier: Operating System :: OS Independent
License-File: LICENSE
Requires-Dist: pydicom
Requires-Dist: pandas
